.DS_Store
pySolution/__init__.py
pySolution/solutionScript.py
pySolution/core/__init__.py
pySolution/core/binary_parameters.xlsx
pySolution/core/debye_huckel_model.py
pySolution/core/density_script.py
pySolution/core/density_temp.pickle
pySolution/core/dielectric_constant.xlsx
pySolution/core/dielectric_model_h2o.pickle
pySolution/core/empirical_parameters.xlsx
pySolution/core/helper_functions.py
pySolution/core/main.py
pySolution/core/mixing_parameters.xlsx
pySolution/core/model_results.py
pySolution/core/osmotic.py
pySolution/core/pitzer_v1.py
pySolution/core/plotting.py
pySolution/core/run_model.py
pySolution/core/water_density.txt
pySolution-0.0.2.1.4.3.dist-info/METADATA
pySolution-0.0.2.1.4.3.dist-info/WHEEL
pySolution-0.0.2.1.4.3.dist-info/top_level.txt
pySolution-0.0.2.1.4.3.dist-info/RECORD
