Metadata-Version: 2.1
Name: pySolution
Version: 0.0.2.1.4.3
Summary: Computes details of solution for modeling purposes
Home-page: https://github.com/sartaajkhan/pySolution
Author: Sartaaj Khan
License: UNKNOWN
Keywords: python,solution chemistry,activity coefficient,osmosis,reverse osmosis,chemistry
Platform: UNKNOWN
Classifier: Development Status :: 1 - Planning
Classifier: Intended Audience :: Developers
Classifier: Programming Language :: Python :: 3
Classifier: Operating System :: Unix
Classifier: Operating System :: MacOS :: MacOS X
Classifier: Operating System :: Microsoft :: Windows
Requires-Dist: numpy
Requires-Dist: pandas
Requires-Dist: scipy
Requires-Dist: joblib
Requires-Dist: proplot
Requires-Dist: matplotlib
Requires-Dist: scikit-learn (==0.24.2)
